{
    "KPlugin": {
        "Description": "KOrganizer Group Scheduling Configuration",
        "Description[ar]": "ضبط جدولة المجموعات لِ‍«منظّمك»",
        "Description[az]": "KOrganizer qrup planlaşdırma tənzimləməsi",
        "Description[bg]": "Настройка на групово разписание на KOrganizer",
        "Description[ca@valencia]": "Configureu la planificació de grups de KOrganizer",
        "Description[ca]": "Configuració de la planificació de grups del KOrganizer",
        "Description[cs]": "Nastavení skupinového plánování KOrganizeru",
        "Description[de]": "Einrichtung von Gruppen-Planungen für KOrganizer",
        "Description[el]": "Διαμόρφωση προγραμματισμού ομάδας του KOrganizer",
        "Description[en_GB]": "KOrganizer Group Scheduling Configuration",
        "Description[eo]": "Agordo por KOrganizer Grupplanado",
        "Description[es]": "Configuración de la planificación de grupos de KOrganizer",
        "Description[eu]": "«KOrganizer»ren Talde Antolaketa konfigurazioa",
        "Description[fi]": "KOrganizerin ryhmäaikatauluasetukset",
        "Description[fr]": "Configuration de la planification des groupes de KOrganizer",
        "Description[gl]": "Configuración da Axenda de Grupo de KOrganizer.",
        "Description[he]": "הגדרות תזמון של KOrganizer",
        "Description[hu]": "KOrganizer szervezési beállítások",
        "Description[ia]": "Configuration KOrganizer de horario de gruppo",
        "Description[id]": "Konfigurasi Penjadwalan Grup KOrganizer",
        "Description[it]": "Configurazione del programmatore gruppi di KOrganizer",
        "Description[ka]": "KOrganizer-ში ჯგუფური განრიგის მორგება",
        "Description[ko]": "KOrganizer 그룹 스케줄링 설정",
        "Description[lv]": "„KOrganizer“ grupu plānošanas konfigurācija",
        "Description[nl]": "KOrganizer groepsplanning instellen",
        "Description[pl]": "Ustawienia planowania grupowego dla KOrganizera",
        "Description[pt]": "Configuração do Escalonamento do Grupo do KOrganizer",
        "Description[pt_BR]": "Configuração de agendamento de grupo do KOrganizer",
        "Description[ru]": "Настройка календаря группы",
        "Description[sa]": "KOrganizer समूह समयनिर्धारण विन्यास",
        "Description[sl]": "Nastavitev razporejanja skupin v KOrganizerju",
        "Description[sv]": "Inställning av Korganizers gruppschemaläggning",
        "Description[tr]": "K Organizatör Grup Zamanlama Yapılandırması",
        "Description[uk]": "Налаштування групового розкладу в KOrganizer",
        "Description[x-test]": "xxKOrganizer Group Scheduling Configurationxx",
        "Description[zh_CN]": "Korganizer 组日程安排配置",
        "Description[zh_TW]": "KOrganizer 群組排程設定",
        "Icon": "network-workgroup",
        "Name": "Group Scheduling",
        "Name[af]": "Groep Skedulering",
        "Name[ar]": "جدولة المجموعات",
        "Name[az]": "Qrup Planlaşdırılması",
        "Name[bg]": "Групово разписание",
        "Name[bs]": "Grupni raspored",
        "Name[ca@valencia]": "Planificació de grups",
        "Name[ca]": "Planificació de grups",
        "Name[cs]": "Skupinové plánování",
        "Name[cy]": "Trefnlennu Grŵp",
        "Name[da]": "Gruppeskemalægning",
        "Name[de]": "Gruppenplanung",
        "Name[el]": "Προγραμματισμός ομάδας",
        "Name[en_GB]": "Group Scheduling",
        "Name[eo]": "Grupoplanado",
        "Name[es]": "Planificación de grupos",
        "Name[et]": "Grupitöö ajakavad",
        "Name[eu]": "Talde antolaketa",
        "Name[fa]": "زمان‌بندی گروه",
        "Name[fi]": "Ryhmän aikataulut",
        "Name[fr]": "Planification des tâches",
        "Name[fy]": "Groepsplanning",
        "Name[ga]": "Sceidealadh Grúpa",
        "Name[gl]": "Organización de grupo",
        "Name[he]": "תזמון קבוצתי",
        "Name[hu]": "Szervezés",
        "Name[ia]": "Horario de gruppo",
        "Name[id]": "Penjadwalan Grup",
        "Name[is]": "Hópáætlun",
        "Name[it]": "Programmazione gruppi",
        "Name[ja]": "グループスケジューリング",
        "Name[ka]": "ჯგუფური განრიგი",
        "Name[kk]": "Топтың жұмысын жоспарлау",
        "Name[km]": "រៀបចំ​កាលវិភាគ​ក្រុម",
        "Name[ko]": "그룹 스케줄링",
        "Name[lt]": "Grupių tvarkaraščių tvarkymas",
        "Name[lv]": "Grupu plānošana",
        "Name[mk]": "Закажување групи",
        "Name[mr]": "समूह नियोजन",
        "Name[ms]": "Penjadualan Kumpulan",
        "Name[nb]": "Gruppeplanlegging",
        "Name[nds]": "Koppelplanen",
        "Name[ne]": "समूह कार्यतालिका",
        "Name[nl]": "Groepsplanning",
        "Name[nn]": "Gruppeplanlegging",
        "Name[pa]": "ਗਰੁੱਪ ਸ਼ੈਡਿਊਲ",
        "Name[pl]": "Planowanie grupowe",
        "Name[pt]": "Calendarização em Grupo",
        "Name[pt_BR]": "Agendamento de grupo",
        "Name[ro]": "Planificare de grup",
        "Name[ru]": "Календарь группы",
        "Name[sa]": "समूह समयनिर्धारण",
        "Name[se]": "Joavkoplánen",
        "Name[sk]": "Skupinové plánovanie",
        "Name[sl]": "Razporejanje skupin",
        "Name[sr@ijekavian]": "Распоређивање група",
        "Name[sr@ijekavianlatin]": "Raspoređivanje grupa",
        "Name[sr@latin]": "Raspoređivanje grupa",
        "Name[sr]": "Распоређивање група",
        "Name[sv]": "Gruppschemaläggning",
        "Name[ta]": "குழு திட்ட வரையறை",
        "Name[tg]": "Ҷадвали гурӯҳҳо",
        "Name[tr]": "Grup Zamanlama",
        "Name[ug]": "گۇرۇپپا پىلانى",
        "Name[uk]": "Розклад груп",
        "Name[wa]": "Programaedje e groupe",
        "Name[x-test]": "xxGroup Schedulingxx",
        "Name[zh_CN]": "组日程安排",
        "Name[zh_TW]": "群組排程"
    },
    "X-DocPath": "korganizer/config.html#config-main-groupscheduling",
    "X-KDE-Weight": 500
}
