{
    "KPlugin": {
        "Description": "Upcoming Events Summary Setup",
        "Description[ar]": "إعداد ملخّص الأحداث القادمة",
        "Description[az]": "Gələcək tədbirlərin xülasəsi ayarları",
        "Description[bg]": "Обобщаващи настройки на предстоящи събития",
        "Description[ca@valencia]": "Configureu el resum dels esdeveniments pròxims",
        "Description[ca]": "Configuració del resum dels esdeveniments pròxims",
        "Description[cs]": "Nastavení souhrnu nadcházejících událostí",
        "Description[de]": "Einstellung der Übersicht über anstehende Termine",
        "Description[el]": "Ρύθμιση σύνοψης επόμενων γεγονότων",
        "Description[en_GB]": "Upcoming Events Summary Setup",
        "Description[eo]": "Agordo por Resumo de Venontaj Eventoj",
        "Description[es]": "Configuración del resumen de los eventos próximos",
        "Description[eu]": "Hurrengo ekitaldien laburpenaren ezarpena",
        "Description[fi]": "Tulevien tapahtumien yhteenvedon asetus",
        "Description[fr]": "Configuration du résumé des évènements à venir",
        "Description[gl]": "Configuración do resumo de vindeiros eventos.",
        "Description[he]": "הגדרות תקציר אירועים קרובים",
        "Description[hu]": "A közelgő események áttekintőjének beállításai",
        "Description[ia]": "Preferentias de summarisar eventos a venir",
        "Description[id]": "Penyiapan Ringkasan Acara Mendatang",
        "Description[it]": "Impostazioni sommario dei prossimi eventi",
        "Description[ka]": "მომავალი ღონისძიებების საერთო მორგება",
        "Description[ko]": "다가오는 이벤트 요약 설정",
        "Description[lv]": "Gaidāmo notikumu kopsavilkuma iestatījumi",
        "Description[nl]": "Overzichtsinstellingen aanstaande evenementen",
        "Description[pl]": "Ustawienia podsumowania nadchodzących zdarzeń",
        "Description[pt]": "Configuração do Resumo dos Próximos Eventos",
        "Description[pt_BR]": "Configuração do resumo dos próximos eventos",
        "Description[ru]": "Настройка дайджеста предстоящих событий",
        "Description[sa]": "आगामी घटनाः सारांशः सेटअपः",
        "Description[sl]": "Nastavi povzetek prihodnjih dogodkov",
        "Description[sv]": "Inställning av översikt över kommande händelser",
        "Description[tr]": "Gelecek etkinlikler özeti yapılandırması",
        "Description[uk]": "Зведення налаштування майбутніх подій",
        "Description[zh_CN]": "近期事件摘要设置",
        "Description[zh_TW]": "將發生的事件摘要設定",
        "Icon": "korganizer",
        "Name": "Upcoming Events",
        "Name[ar]": "الأحداث القادمة",
        "Name[az]": "Gələcək tədbirlər",
        "Name[bg]": "Предстоящи събития",
        "Name[bs]": "Nastupajući događaji",
        "Name[ca@valencia]": "Esdeveniments pròxims",
        "Name[ca]": "Esdeveniments pròxims",
        "Name[cs]": "Nadcházející události",
        "Name[da]": "Kommende begivenheder",
        "Name[de]": "Anstehende Termine",
        "Name[el]": "Επόμενα γεγονότα",
        "Name[en_GB]": "Upcoming Events",
        "Name[eo]": "Venontaj Eventoj",
        "Name[es]": "Próximos eventos",
        "Name[et]": "Tulevased sündmused",
        "Name[eu]": "Hurrengo Ekitaldiak",
        "Name[fi]": "Tulevat tapahtumat",
        "Name[fr]": "Prochains évènements",
        "Name[ga]": "Imeachtaí atá ag teacht",
        "Name[gl]": "Vindeiros eventos",
        "Name[he]": "אירועים קרובים",
        "Name[hu]": "Események a közeljövőben",
        "Name[ia]": "Eventos a venir",
        "Name[id]": "Acara Mendatang",
        "Name[it]": "Prossimi eventi",
        "Name[ja]": "近日中のイベント",
        "Name[ka]": "უახლოესი მოვლენები",
        "Name[kk]": "Болашақ оқиғалар",
        "Name[km]": "ព្រឹត្តិការណ៍​ដែល​នឹង​កើតឡើង",
        "Name[ko]": "다가오는 이벤트",
        "Name[lt]": "Artėjantys įvykiai",
        "Name[lv]": "Gaidāmie notikumi",
        "Name[mr]": "पुढे येणाऱ्या घटना",
        "Name[nb]": "Kommende hendelser",
        "Name[nds]": "Anstahn Begeefnissen",
        "Name[ne]": "सम्भावित घटना",
        "Name[nl]": "Nabije evenementen",
        "Name[nn]": "Kommande hendingar",
        "Name[pa]": "ਆ ਰਹੇ ਈਵੈਂਟ",
        "Name[pl]": "Nadchodzące zdarzenia",
        "Name[pt]": "Próximos Eventos",
        "Name[pt_BR]": "Próximos eventos",
        "Name[ro]": "Evenimente apropiate",
        "Name[ru]": "Предстоящие события",
        "Name[sa]": "आगामी घटनाः",
        "Name[sk]": "Nové udalosti",
        "Name[sl]": "Prihodnji dogodki",
        "Name[sr@ijekavian]": "Наступајући догађаји",
        "Name[sr@ijekavianlatin]": "Nastupajući događaji",
        "Name[sr@latin]": "Nastupajući događaji",
        "Name[sr]": "Наступајући догађаји",
        "Name[sv]": "Kommande händelser",
        "Name[ta]": "வரவிருக்கும் நிகழ்வுகள்",
        "Name[th]": "เหตุการณ์ที่ใกล้จะมาถึง",
        "Name[tr]": "Yaklaşan Etkinlikler",
        "Name[ug]": "پىلاندىكى ھادىسىلەر",
        "Name[uk]": "Майбутні події",
        "Name[wa]": "Evenmints a vni",
        "Name[zh_CN]": "近期事件",
        "Name[zh_TW]": "將發生的事件"
    },
    "X-KDE-Weight": 400
}
